binalyzer_patch/__init__.py
binalyzer_patch/cli.py
binalyzer_patch/extension.py
binalyzer_patch-0.0.1.data/data/CHANGELOG.md
binalyzer_patch-0.0.1.dist-info/AUTHORS
binalyzer_patch-0.0.1.dist-info/LICENSE.rst
binalyzer_patch-0.0.1.dist-info/METADATA
binalyzer_patch-0.0.1.dist-info/WHEEL
binalyzer_patch-0.0.1.dist-info/entry_points.txt
binalyzer_patch-0.0.1.dist-info/top_level.txt
binalyzer_patch-0.0.1.dist-info/RECORD
